calcure/__main__.py
calcure/calendars.py
calcure/colors.py
calcure/configuration.py
calcure/controls.py
calcure/data.py
calcure/dialogues.py
calcure/errors.py
calcure/importers.py
calcure/input.py
calcure/loaders.py
calcure/moon.py
calcure/savers.py
calcure/screen.py
calcure/test.py
calcure/weather.py
calcure/translations/br.py
calcure/translations/en.py
calcure/translations/fr.py
calcure/translations/it.py
calcure/translations/ru.py
calcure/translations/sk.py
calcure/translations/tr.py
calcure/translations/tw.py
calcure/translations/zh.py
calcure-3.2.1.data/data/share/man/man1/calcure.1.gz
calcure-3.2.1.dist-info/licenses/LICENSE
calcure-3.2.1.dist-info/METADATA
calcure-3.2.1.dist-info/WHEEL
calcure-3.2.1.dist-info/entry_points.txt
calcure-3.2.1.dist-info/top_level.txt
calcure-3.2.1.dist-info/RECORD
