Metadata-Version: 2.4
Name: calcure
Version: 3.2.1
Summary: Modern TUI calendar and task manager
Home-page: https://github.com/anufrievroman/calcure
Author: Roman Anufriev
Author-email: anufriev.roman@protonmail.com
License: MIT
Classifier: Development Status :: 4 - Beta
Classifier: License :: OSI Approved :: MIT License
Classifier: Environment :: Console
Classifier: Natural Language :: English
Classifier: Operating System :: OS Independent
Classifier: Programming Language :: Python :: 3.9
Classifier: Programming Language :: Python :: 3.10
Classifier: Programming Language :: Python :: 3.11
Classifier: Programming Language :: Python :: 3.12
Classifier: Programming Language :: Python :: 3.13
Classifier: Topic :: Utilities
Requires-Python: ~=3.9
License-File: LICENSE
Requires-Dist: holidays
Requires-Dist: jdatetime
Requires-Dist: icalendar
Dynamic: author
Dynamic: author-email
Dynamic: classifier
Dynamic: description
Dynamic: description-content-type
Dynamic: home-page
Dynamic: license
Dynamic: license-file
Dynamic: requires-dist
Dynamic: requires-python
Dynamic: summary
